defipulsedata/__init__.py
defipulsedata/defi_pulse.py
defipulsedata/dex_ag.py
defipulsedata/eth_gas_station.py
defipulsedata/pools_fyi.py
defipulsedata/rek_to.py
defipulsedata/utils.py
defipulsedata-0.0.0.dist-info/entry_points.txt
defipulsedata-0.0.0.dist-info/LICENSE
defipulsedata-0.0.0.dist-info/WHEEL
defipulsedata-0.0.0.dist-info/METADATA
defipulsedata-0.0.0.dist-info/RECORD
