Metadata-Version: 2.1
Name: defipulsedata
Version: 0.0.0
Summary: Unofficial SDK for DeFi Pulse Data
Home-page: https://pypi.org/project/defipulsedata
License: MIT
Keywords: DeFi,Decentralized Finance,SDK,Client
Author: James Boyle
Author-email: pydefipulsedata@protonmail.com
Requires-Python: >=3.7,<4.0
Classifier: License :: OSI Approved :: MIT License
Classifier: Programming Language :: Python :: 3
Classifier: Programming Language :: Python :: 3.7
Classifier: Programming Language :: Python :: 3.8
Classifier: Programming Language :: Python :: 3.9
Requires-Dist: click (>=7.0,<8.0)
Requires-Dist: minilog (>=2.0,<3.0)
Requires-Dist: responses (>=0.13.3,<0.14.0)
Project-URL: Documentation, https://defipulsedata.readthedocs.io
Project-URL: Repository, https://github.com/jhhb/pydefipulsedata
